plastron/context/__init__.py
plastron/files/__init__.py
plastron/repo/__init__.py
plastron/repo/pcdm.py
plastron/repo/publish.py
plastron/repo/utils.py
plastron_repo-4.6.2.dist-info/METADATA
plastron_repo-4.6.2.dist-info/WHEEL
plastron_repo-4.6.2.dist-info/top_level.txt
plastron_repo-4.6.2.dist-info/RECORD
