Metadata-Version: 2.4
Name: plastron-repo
Version: 4.6.2
Summary: High-level classes and functions for interacting with a Fedora repository
Author-email: University of Maryland Libraries <lib-ssdr@umd.edu>, Josh Westgard <westgard@umd.edu>, Peter Eichman <peichman@umd.edu>, Mohamed Abdul Rasheed <mohideen@umd.edu>, Ben Wallberg <wallberg@umd.edu>, David Steelman <dsteelma@umd.edu>, Marc Andreu Grillo Aguilar <aguilarm@umd.edu>
Requires-Python: >=3.10
Requires-Dist: paramiko
Requires-Dist: plastron-client
Requires-Dist: plastron-messaging
Requires-Dist: plastron-models
Requires-Dist: plastron-utils
Requires-Dist: pysolr
Requires-Dist: PyYAML
Requires-Dist: rdflib
Requires-Dist: requests
Requires-Dist: URLObject
Provides-Extra: test
Requires-Dist: freezegun; extra == "test"
Requires-Dist: pytest; extra == "test"
Requires-Dist: pytest-cov; extra == "test"
Requires-Dist: pytest-datadir; extra == "test"
